seeta_dragon-0.3.0.data/purelib/dragon/__init__.py
seeta_dragon-0.3.0.data/purelib/dragon/version.py
seeta_dragon-0.3.0.data/purelib/dragon/_api/__init__.py
seeta_dragon-0.3.0.data/purelib/dragon/_api/autograph/__init__.py
seeta_dragon-0.3.0.data/purelib/dragon/_api/bitwise/__init__.py
seeta_dragon-0.3.0.data/purelib/dragon/_api/cuda/__init__.py
seeta_dragon-0.3.0.data/purelib/dragon/_api/distributed/__init__.py
seeta_dragon-0.3.0.data/purelib/dragon/_api/dlpack/__init__.py
seeta_dragon-0.3.0.data/purelib/dragon/_api/logging/__init__.py
seeta_dragon-0.3.0.data/purelib/dragon/_api/losses/__init__.py
seeta_dragon-0.3.0.data/purelib/dragon/_api/math/__init__.py
seeta_dragon-0.3.0.data/purelib/dragon/_api/metrics/__init__.py
seeta_dragon-0.3.0.data/purelib/dragon/_api/mps/__init__.py
seeta_dragon-0.3.0.data/purelib/dragon/_api/nn/__init__.py
seeta_dragon-0.3.0.data/purelib/dragon/_api/onnx/__init__.py
seeta_dragon-0.3.0.data/purelib/dragon/_api/optimizers/__init__.py
seeta_dragon-0.3.0.data/purelib/dragon/_api/random/__init__.py
seeta_dragon-0.3.0.data/purelib/dragon/_api/sysconfig/__init__.py
seeta_dragon-0.3.0.data/purelib/dragon/_api/vision/__init__.py
seeta_dragon-0.3.0.data/purelib/dragon/core/__init__.py
seeta_dragon-0.3.0.data/purelib/dragon/core/autograph/__init__.py
seeta_dragon-0.3.0.data/purelib/dragon/core/autograph/backprop.py
seeta_dragon-0.3.0.data/purelib/dragon/core/autograph/config.py
seeta_dragon-0.3.0.data/purelib/dragon/core/autograph/context.py
seeta_dragon-0.3.0.data/purelib/dragon/core/autograph/function_lib.py
seeta_dragon-0.3.0.data/purelib/dragon/core/autograph/graph_lib.py
seeta_dragon-0.3.0.data/purelib/dragon/core/autograph/op_args.py
seeta_dragon-0.3.0.data/purelib/dragon/core/autograph/op_lib.py
seeta_dragon-0.3.0.data/purelib/dragon/core/autograph/op_schema.py
seeta_dragon-0.3.0.data/purelib/dragon/core/autograph/op_spec.py
seeta_dragon-0.3.0.data/purelib/dragon/core/device/__init__.py
seeta_dragon-0.3.0.dist-info/METADATA
seeta_dragon-0.3.0.dist-info/WHEEL
seeta_dragon-0.3.0.dist-info/top_level.txt
seeta_dragon-0.3.0.dist-info/RECORD
